fau_tools/__init__.py
fau_tools/data_structure/__init__.py
fau_tools/data_structure/_model_manager.py
fau_tools/data_structure/_scalar_recorder.py
fau_tools/data_structure/_task_runner.py
fau_tools/data_structure/_time_manager.py
fau_tools/torch_tools/__init__.py
fau_tools/torch_tools/_torch_tools.py
fau_tools/utils/__init__.py
fau_tools/utils/_color_print.py
fau_tools/utils/_device.py
fau_tools/utils/_utils.py
fau_tools-2.0.4.dist-info/METADATA
fau_tools-2.0.4.dist-info/WHEEL
fau_tools-2.0.4.dist-info/RECORD
