Metadata-Version: 2.1
Name: fau-tools
Version: 2.0.4
Summary: A python module. The main function is for pytorch training.
Home-page: https://github.com/Fau818/fau-tools
License: MIT
Author: Fau
Author-email: Fau818@qq.com
Requires-Python: >=3.10
Classifier: License :: OSI Approved :: MIT License
Classifier: Programming Language :: Python :: 3
Classifier: Programming Language :: Python :: 3.10
Classifier: Programming Language :: Python :: 3.11
Classifier: Programming Language :: Python :: 3.12
Project-URL: Repository, https://github.com/Fau818/fau-tools
